datamuse/__init__.py
datamuse/datamuse.py
python_datamuse-1.3.2.dist-info/LICENSE
python_datamuse-1.3.2.dist-info/METADATA
python_datamuse-1.3.2.dist-info/WHEEL
python_datamuse-1.3.2.dist-info/top_level.txt
python_datamuse-1.3.2.dist-info/RECORD
