Metadata-Version: 2.1
Name: python-datamuse
Version: 1.3.2
Summary: Python wrapper for the Datamuse API
Home-page: https://github.com/gmarmstrong/python-datamuse
Author: Guthrie McAfee Armstrong
Author-email: guthrie.armstrong@gmail.com
License: MIT
Keywords: datamuse,linguistics,language,wrapper
Platform: UNKNOWN
Classifier: Development Status :: 3 - Alpha
Classifier: Intended Audience :: Developers
Classifier: License :: OSI Approved :: MIT License
Classifier: Programming Language :: Python :: 3
Requires-Python: >=3.6
License-File: LICENSE
Requires-Dist: requests
